{
  "verification_date": "2025-08-06T13:31:28.238995",
  "system_info": {},
  "checks_passed": 48,
  "checks_failed": 9,
  "total_checks": 8,
  "results": [
    "[2025-08-06 13:31:27] [INFO] \u2705 System: Linux #1 SMP PREEMPT_DYNAMIC Tue Aug  5 21:01:56 UTC 2025",
    "[2025-08-06 13:31:27] [INFO] \u2705 Architecture: x86_64",
    "[2025-08-06 13:31:27] [INFO] \u2705 Python: 3.13.3",
    "[2025-08-06 13:31:27] [INFO] \u2705 Working Directory: /workspace",
    "[2025-08-06 13:31:27] [INFO] \u2705 System information saved to system_info.json",
    "[2025-08-06 13:31:27] [INFO] \u2705 AMP Authentication found",
    "[2025-08-06 13:31:27] [INFO] \u2705 User ID: 01K1XBP8C5SZXYP88QD166AX1W",
    "[2025-08-06 13:31:27] [INFO] \u2705 Expires: 2025-08-07T09:40:37.662863",
    "[2025-08-06 13:31:27] [INFO] \u2705 Session is valid",
    "[2025-08-06 13:31:27] [INFO] \n\ud83d\udcc1 Checking Railway Backend files:",
    "[2025-08-06 13:31:27] [INFO]   \u2705 railway.json",
    "[2025-08-06 13:31:27] [INFO]   \u2705 Dockerfile.railway",
    "[2025-08-06 13:31:27] [INFO]   \u2705 railway.env.template",
    "[2025-08-06 13:31:27] [INFO]   \u2705 Railway Backend - All files present",
    "[2025-08-06 13:31:27] [INFO] \n\ud83d\udcc1 Checking Supabase Database files:",
    "[2025-08-06 13:31:27] [INFO]   \u2705 database/schema.sql",
    "[2025-08-06 13:31:27] [INFO]   \u2705 supabase_config.json",
    "[2025-08-06 13:31:27] [INFO]   \u2705 Supabase Database - All files present",
    "[2025-08-06 13:31:27] [INFO] \n\ud83d\udcc1 Checking Oracle Cloud files:",
    "[2025-08-06 13:31:27] [INFO]   \u2705 docker-compose.oracle.yml",
    "[2025-08-06 13:31:27] [INFO]   \u2705 oracle-deploy.sh",
    "[2025-08-06 13:31:27] [INFO]   \u2705 oracle_config.json",
    "[2025-08-06 13:31:27] [INFO]   \u2705 Oracle Cloud - All files present",
    "[2025-08-06 13:31:27] [INFO] \n\ud83d\udcc1 Checking Google Cloud files:",
    "[2025-08-06 13:31:27] [INFO]   \u2705 cloudbuild.yaml",
    "[2025-08-06 13:31:27] [INFO]   \u2705 Dockerfile.gcp",
    "[2025-08-06 13:31:27] [INFO]   \u2705 gcp_config.json",
    "[2025-08-06 13:31:27] [INFO]   \u2705 Google Cloud - All files present",
    "[2025-08-06 13:31:27] [INFO] \n\ud83d\udcc1 Checking Vercel Frontend files:",
    "[2025-08-06 13:31:27] [INFO]   \u2705 vercel.json",
    "[2025-08-06 13:31:27] [INFO]   \u2705 Vercel Frontend - All files present",
    "[2025-08-06 13:31:27] [INFO] \n\ud83d\udcc1 Checking Deployment Summary files:",
    "[2025-08-06 13:31:27] [INFO]   \u2705 deployment_summary.json",
    "[2025-08-06 13:31:27] [INFO]   \u2705 Deployment Summary - All files present",
    "[2025-08-06 13:31:27] [ERROR] \u274c Docker check failed: [Errno 2] No such file or directory: 'docker'",
    "[2025-08-06 13:31:27] [ERROR] \u274c Railway CLI not found",
    "[2025-08-06 13:31:27] [ERROR] \u274c Google Cloud CLI not found",
    "[2025-08-06 13:31:27] [ERROR] \u274c Vercel CLI not found",
    "[2025-08-06 13:31:27] [INFO] \u2705 Node.js: v22.16.0",
    "[2025-08-06 13:31:27] [INFO] \u2705 npm: 10.9.2",
    "[2025-08-06 13:31:27] [INFO] \n\ud83d\udca1 Installation commands:",
    "[2025-08-06 13:31:27] [INFO]   Railway CLI: npm install -g @railway/cli",
    "[2025-08-06 13:31:27] [INFO]   Google Cloud CLI: curl https://sdk.cloud.google.com | bash",
    "[2025-08-06 13:31:27] [INFO]   Vercel CLI: npm install -g vercel",
    "[2025-08-06 13:31:27] [INFO]   Node.js: https://nodejs.org/",
    "[2025-08-06 13:31:27] [INFO] \u2705 requirements.txt found",
    "[2025-08-06 13:31:27] [INFO] \u2705 requests",
    "[2025-08-06 13:31:27] [ERROR] \u274c numpy - MISSING",
    "[2025-08-06 13:31:27] [ERROR] \u274c pandas - MISSING",
    "[2025-08-06 13:31:27] [ERROR] \u274c scikit-learn - MISSING",
    "[2025-08-06 13:31:27] [INFO] \u2705 asyncio",
    "[2025-08-06 13:31:27] [ERROR] \u274c aiohttp - MISSING",
    "[2025-08-06 13:31:27] [ERROR] \u274c websockets - MISSING",
    "[2025-08-06 13:31:27] [INFO] \n\ud83d\udca1 Install missing dependencies:",
    "[2025-08-06 13:31:27] [INFO]   pip install numpy pandas scikit-learn aiohttp websockets",
    "[2025-08-06 13:31:27] [INFO] \u2705 GitHub: Connected",
    "[2025-08-06 13:31:27] [INFO] \u2705 Railway: Connected",
    "[2025-08-06 13:31:27] [INFO] \u2705 Supabase: Connected",
    "[2025-08-06 13:31:27] [INFO] \u2705 Oracle Cloud: Connected",
    "[2025-08-06 13:31:28] [INFO] \u2705 Google Cloud: Connected",
    "[2025-08-06 13:31:28] [INFO] \u2705 Vercel: Connected",
    "[2025-08-06 13:31:28] [INFO] \u2705 Deployment Date: 2025-08-06T09:42:28.620233",
    "[2025-08-06 13:31:28] [INFO] \u2705 AMP User: 01K1XBP8C5SZXYP88QD166AX1W",
    "[2025-08-06 13:31:28] [INFO] \u2705 Phases Completed: 5/5",
    "[2025-08-06 13:31:28] [INFO] \u2705 Total Monthly Cost: $6-10",
    "[2025-08-06 13:31:28] [INFO] \u2705 backend (Railway): $5/month - configured",
    "[2025-08-06 13:31:28] [INFO] \u2705 database (Supabase): FREE - configured",
    "[2025-08-06 13:31:28] [INFO] \u2705 ai_processing (Oracle Cloud): FREE - configured",
    "[2025-08-06 13:31:28] [INFO] \u2705 signal_processing (Google Cloud Run): $1-5/month - configured",
    "[2025-08-06 13:31:28] [INFO] \u2705 frontend (Vercel): FREE - configured",
    "[2025-08-06 13:31:28] [INFO] \n\ud83d\udccb Next Steps:",
    "[2025-08-06 13:31:28] [INFO]   1. 1. Set up Oracle Cloud account and create VM instance",
    "[2025-08-06 13:31:28] [INFO]   2. 2. Update supabase_config.json with your Supabase credentials",
    "[2025-08-06 13:31:28] [INFO]   3. 3. Update gcp_config.json with your GCP project details",
    "[2025-08-06 13:31:28] [INFO]   4. 4. Run ./oracle-deploy.sh on your Oracle Cloud instance",
    "[2025-08-06 13:31:28] [INFO]   5. 5. Deploy to Railway: railway up",
    "[2025-08-06 13:31:28] [INFO]   6. 6. Deploy to Google Cloud: gcloud builds submit",
    "[2025-08-06 13:31:28] [INFO]   7. 7. Deploy to Vercel: vercel --prod",
    "[2025-08-06 13:31:28] [INFO] \n\ud83d\udcca Generating verification report..."
  ],
  "recommendations": [
    "Fix failed checks before deployment",
    "System is ready for deployment"
  ]
}